NuOCR/__init__.py
NuOCR/admin.py
NuOCR/channel.py
NuOCR/extractor.py
NuOCR/io_adaptor.py
NuOCR/monitor.py
NuOCR/multiformats.py
NuOCR/preprocessors.py
NuOCR/templated_flow.py
NuOCR/text.py
NuOCR/user.py
NuOCR/util.py
NuOCR/gRPC_proto/__init__.py
NuOCR/gRPC_proto/extractor/__init__.py
NuOCR/gRPC_proto/extractor/extractor_pb2.py
NuOCR/gRPC_proto/extractor/extractor_pb2_grpc.py
NuOCR/gRPC_proto/io_adaptors/__init__.py
NuOCR/gRPC_proto/io_adaptors/io_adaptors_pb2.py
NuOCR/gRPC_proto/io_adaptors/io_adaptors_pb2_grpc.py
NuOCR/gRPC_proto/monitor/__init__.py
NuOCR/gRPC_proto/monitor/monitor_pb2.py
NuOCR/gRPC_proto/monitor/monitor_pb2_grpc.py
NuOCR/gRPC_proto/multiformats/__init__.py
NuOCR/gRPC_proto/multiformats/multiformats_pb2.py
NuOCR/gRPC_proto/multiformats/multiformats_pb2_grpc.py
NuOCR/gRPC_proto/nufarm_poc/__init__.py
NuOCR/gRPC_proto/nufarm_poc/nufarm_poc_pb2.py
NuOCR/gRPC_proto/nufarm_poc/nufarm_poc_pb2_grpc.py
NuOCR/gRPC_proto/preprocessor/__init__.py
NuOCR/gRPC_proto/preprocessor/preprocessor_pb2.py
NuOCR/gRPC_proto/preprocessor/preprocessor_pb2_grpc.py
NuOCR/gRPC_proto/templated_flow/__init__.py
NuOCR/gRPC_proto/templated_flow/templated_flow_pb2.py
NuOCR/gRPC_proto/templated_flow/templated_flow_pb2_grpc.py
NuOCR/gRPC_proto/text_processor/__init__.py
NuOCR/gRPC_proto/text_processor/text_processor_pb2.py
NuOCR/gRPC_proto/text_processor/text_processor_pb2_grpc.py
NuOCR/gRPC_proto/text_processors/__init__.py
NuOCR/gRPC_proto/text_processors/text_processor_pb2.py
NuOCR/gRPC_proto/text_processors/text_processor_pb2_grpc.py
NuOCR/gRPC_proto/user/__init__.py
NuOCR/gRPC_proto/user/auth_pb2.py
NuOCR/gRPC_proto/user/auth_pb2_grpc.py
NuOCR/gRPC_proto/user/user_pb2.py
NuOCR/gRPC_proto/user/user_pb2_grpc.py
NuOCR-0.2.5.3.dist-info/METADATA
NuOCR-0.2.5.3.dist-info/WHEEL
NuOCR-0.2.5.3.dist-info/top_level.txt
NuOCR-0.2.5.3.dist-info/RECORD
