Metadata-Version: 2.1
Name: NuOCR
Version: 0.2.5.3
Summary: Using NuOCR service via APIs
Author: Nuvento Systems Pvt. Ltd. (Jigar Makwana)
Author-email: <makwana.jigar@nuvento.com>
Keywords: python,NuOCR,OCR
Classifier: Development Status :: 1 - Planning
Classifier: Intended Audience :: Developers
Classifier: Programming Language :: Python :: 3
Classifier: Operating System :: Unix
Classifier: Operating System :: MacOS :: MacOS X
Classifier: Operating System :: Microsoft :: Windows
Requires-Dist: grpcio
Requires-Dist: protobuf
